src/__init__.py
src/htsinfer.py
htsinfer-0.2.0.dist-info/LICENSE
htsinfer-0.2.0.dist-info/METADATA
htsinfer-0.2.0.dist-info/WHEEL
htsinfer-0.2.0.dist-info/entry_points.txt
htsinfer-0.2.0.dist-info/top_level.txt
htsinfer-0.2.0.dist-info/RECORD
