Metadata-Version: 2.1
Name: htsinfer
Version: 0.2.0
Summary: HTSinfer infers metadata from High Throughput Sequencing (HTS) data
Home-page: https://github.com/zavolanlab/htsinfer
Author: Rohan Kandhari
Author-email: rohan.kandhari.bme16@iitbhu.ac.in
Maintainer: Rohan Kandhari
Maintainer-email: rohan.kandhari.bme16@iitbhu.ac.in
License: UNKNOWN
Project-URL: Repository, https://github.com/zavolanlab/htsinfer
Project-URL: Tracker, https://github.com/zavolanlab/htsinfer/issues
Keywords: bioinformatics,ngs,high-throughput sequencing,inference
Platform: UNKNOWN
Classifier: Environment :: Console
Classifier: Intended Audience :: Science/Research
Classifier: License :: OSI Approved :: Apache Software License
Classifier: Natural Language :: English
Classifier: Programming Language :: Python :: 3 :: Only
Classifier: Topic :: Scientific/Engineering :: Bio-Informatics
Classifier: Topic :: Utilities
Requires-Dist: coverage (==5.0.3)
Requires-Dist: coveralls (==1.11.1)
Requires-Dist: flake8 (==3.7.9)
Requires-Dist: pylint (==2.4.4)
Requires-Dist: pytest (==5.3.2)
Requires-Dist: setuptools (==46.4.0)
Requires-Dist: twine (==3.1.1)
